README.md
setup.py
docs/__init__.py
halo_bian/__init__.py
halo_bian/config.py
halo_bian.egg-info/PKG-INFO
halo_bian.egg-info/SOURCES.txt
halo_bian.egg-info/dependency_links.txt
halo_bian.egg-info/top_level.txt
halo_bian/bian/__init__.py
halo_bian/bian/bian.py
halo_bian/bian/bian_foi.py
halo_bian/bian/db.py
halo_bian/bian/exceptions.py
halo_bian/bian/filter.py
halo_bian/bian/util.py
halo_bian/bian/app/__init__.py
halo_bian/bian/app/command.py
halo_bian/bian/app/context.py
halo_bian/bian/app/err_msg.py
halo_bian/bian/app/handler.py
halo_bian/bian/app/query.py
halo_bian/bian/app/request.py
halo_bian/bian/app/response.py
halo_bian/bian/domain/__init__.py
halo_bian/bian/domain/event.py
halo_bian/bian/domain/model.py
halo_bian/bian/infra/__init__.py
halo_bian/bian/infra/sql_orm.py
halo_bian/bian/plugins/halo_bian_config_plugin.py
halo_bian/bian/plugins/halo_bian_defs_plugin.py
halo_bian/bian/plugins/halo_bian_err_plugin.py
halo_bian/bian/plugins/halo_bian_mixin_plugin.py