Metadata-Version: 2.1
Name: halo-bian
Version: 0.12.52
Summary: this is the Halo Bian library
Home-page: https://github.com/halo-framework/halo-bian
Author: halo-framework
Author-email: halo-framework@gmail.com
License: MIT License
Platform: UNKNOWN
Classifier: Environment :: Console
Classifier: License :: OSI Approved :: MIT License
Classifier: Operating System :: OS Independent
Classifier: Programming Language :: Python :: 3.7
Classifier: Topic :: Internet :: WWW/HTTP
Classifier: Topic :: Internet :: WWW/HTTP :: Dynamic Content
